decmore/__init__.py
decmore/default.py
decmore/memo.py
decmore/param_type.py
decmore/profiler.py
decmore/thread.py
decmore-1.1.2.dist-info/LICENSE.md
decmore-1.1.2.dist-info/METADATA
decmore-1.1.2.dist-info/WHEEL
decmore-1.1.2.dist-info/top_level.txt
decmore-1.1.2.dist-info/RECORD
