Metadata-Version: 2.1
Name: decmore
Version: 1.1.2
Summary: Useful decorators for your application.
Home-page: https://github.com/DanielTrivelli/decmore
Author: Daniel Trivelli
Author-email: Daniel Trivelli <daniel.trivelli@icloud.com>
License: MIT License
Classifier: Intended Audience :: Developers
Classifier: License :: OSI Approved :: MIT License
Classifier: Operating System :: OS Independent
Classifier: Programming Language :: Python
Classifier: Programming Language :: Python :: 3
Classifier: Programming Language :: Python :: 3 :: Only
Classifier: Programming Language :: Python :: 3.7
Classifier: Programming Language :: Python :: 3.8
Classifier: Programming Language :: Python :: 3.9
Classifier: Programming Language :: Python :: 3.10
Classifier: Topic :: Software Development :: Libraries
Requires-Python: >=3.7
License-File: LICENSE.md
Requires-Dist: numpy ~=1.26.1
Provides-Extra: doc
Requires-Dist: Sphinx <2,>=1.6.5 ; extra == 'doc'
Requires-Dist: sphinx-rtd-theme >=0.1.9 ; extra == 'doc'
